edd_utils/__init__.py
edd_utils-0.0.12.dist-info/LICENSE.txt
edd_utils-0.0.12.dist-info/METADATA
edd_utils-0.0.12.dist-info/WHEEL
edd_utils-0.0.12.dist-info/entry_points.txt
edd_utils-0.0.12.dist-info/top_level.txt
edd_utils-0.0.12.dist-info/RECORD
