Metadata-Version: 2.1
Name: edd-utils
Version: 0.0.12
Summary: Download Studies from an Experiment Data Depot Instance
Home-page: https://github.com/JBEI/edd-utils
Author: Zak Costello, William Morrell, Mark Forrer, Tijana Radivojevic, Reinhard Gentz
Author-email: tradivojevic@lbl.gov
License: BSD
Platform: UNKNOWN
Classifier: Programming Language :: Python :: 3.6
Classifier: Intended Audience :: Science/Research
Requires-Python: >=3.6.5
Requires-Dist: tqdm (>=4.25.0)
Requires-Dist: pandas
Requires-Dist: requests
